{"stats":{"minecraft:used":{"minecraft:iron_shovel":393,"minecraft:stone_shovel":295,"minecraft:ladder":8,"minecraft:chest":2,"minecraft:stone_hoe":279,"minecraft:rotten_flesh":9,"minecraft:orange_bed":14,"minecraft:torch":36,"minecraft:dirt":702,"minecraft:golden_shovel":32,"minecraft:granite":1,"minecraft:wooden_axe":62,"minecraft:villager_spawn_egg":9,"minecraft:iron_axe":314,"minecraft:acacia_slab":190,"minecraft:furnace":2,"minecraft:minecart":4,"minecraft:egg":1,"minecraft:potato":5,"minecraft:acacia_planks":254,"minecraft:golden_axe":36,"minecraft:wheat_seeds":165,"minecraft:short_grass":1,"minecraft:acacia_boat":10,"minecraft:water_bucket":44,"minecraft:cobblestone_stairs":17,"minecraft:acacia_trapdoor":17,"minecraft:stone_pickaxe":131,"minecraft:oak_planks":8,"minecraft:composter":4,"minecraft:rail":15,"minecraft:crafting_table":7,"minecraft:dripstone_block":4,"minecraft:apple":3,"minecraft:acacia_door":1,"minecraft:melon_slice":59,"minecraft:bread":16,"minecraft:iron_pickaxe":670,"minecraft:stone_axe":123,"minecraft:cobblestone":197,"minecraft:bucket":44},"minecraft:dropped":{"minecraft:cobblestone":22,"minecraft:stick":4,"minecraft:dirt":2,"minecraft:torch":1,"minecraft:melon_slice":35,"minecraft:bone_meal":1,"minecraft:iron_pickaxe":2,"minecraft:orange_bed":1,"minecraft:iron_shovel":4,"minecraft:string":4,"minecraft:acacia_planks":25,"minecraft:stone_axe":3,"minecraft:wheat":8,"minecraft:stone_shovel":1,"minecraft:rotten_flesh":20,"minecraft:potato":764,"minecraft:gunpowder":2,"minecraft:acacia_slab":2,"minecraft:spider_eye":20,"minecraft:arrow":2,"minecraft:cartography_table":2},"minecraft:killed":{"minecraft:armadillo":1,"minecraft:spider":4,"minecraft:skeleton":4,"minecraft:creeper":2,"minecraft:zombie":10,"minecraft:villager":8},"minecraft:killed_by":{"minecraft:spider":1,"minecraft:skeleton":1,"minecraft:zombie":1},"minecraft:custom":{"minecraft:mob_kills":29,"minecraft:interact_with_crafting_table":55,"minecraft:leave_game":7,"minecraft:time_since_death":87674,"minecraft:climb_one_cm":5863,"minecraft:sprint_one_cm":404212,"minecraft:walk_one_cm":691985,"minecraft:drop":67,"minecraft:talked_to_villager":7,"minecraft:play_time":264869,"minecraft:deaths":8,"minecraft:sneak_time":7353,"minecraft:walk_under_water_one_cm":3285,"minecraft:boat_one_cm":336501,"minecraft:jump":3275,"minecraft:walk_on_water_one_cm":78010,"minecraft:total_world_time":264869,"minecraft:interact_with_furnace":8,"minecraft:sleep_in_bed":3,"minecraft:time_since_rest":87700,"minecraft:damage_taken":3460,"minecraft:minecart_one_cm":431,"minecraft:damage_dealt":5765,"minecraft:fly_one_cm":597738,"minecraft:open_chest":37,"minecraft:crouch_one_cm":20848,"minecraft:fall_one_cm":89362},"minecraft:mined":{"minecraft:farmland":75,"minecraft:cobblestone_stairs":5,"minecraft:ladder":5,"minecraft:granite":37,"minecraft:acacia_log":93,"minecraft:grass_block":332,"minecraft:acacia_slab":98,"minecraft:composter":2,"minecraft:furnace":1,"minecraft:acacia_trapdoor":13,"minecraft:iron_ore":41,"minecraft:acacia_wood":1,"minecraft:acacia_stairs":2,"minecraft:andesite":15,"minecraft:dirt_path":8,"minecraft:rail":15,"minecraft:stone":498,"minecraft:orange_bed":12,"minecraft:acacia_leaves":25,"minecraft:crafting_table":1,"minecraft:torch":7,"minecraft:short_grass":356,"minecraft:melon":20,"minecraft:chest":6,"minecraft:cobblestone":68,"minecraft:tall_grass":23,"minecraft:oak_planks":8,"minecraft:diorite":2,"minecraft:wall_torch":2,"minecraft:wheat":78,"minecraft:oak_log":6,"minecraft:coal_ore":95,"minecraft:acacia_door":1,"minecraft:gravel":5,"minecraft:dripstone_block":7,"minecraft:dirt":360,"minecraft:acacia_planks":153,"minecraft:oak_leaves":2},"minecraft:picked_up":{"minecraft:crafting_table":1,"minecraft:wheat":8,"minecraft:ladder":5,"minecraft:string":4,"minecraft:acacia_door":1,"minecraft:cartography_table":4,"minecraft:bucket":1,"minecraft:iron_pickaxe":2,"minecraft:minecart":4,"minecraft:melon_slice":94,"minecraft:chest":6,"minecraft:egg":1,"minecraft:stick":22,"minecraft:raw_iron":41,"minecraft:composter":2,"minecraft:torch":74,"minecraft:acacia_log":92,"minecraft:diorite":2,"minecraft:orange_bed":16,"minecraft:arrow":8,"minecraft:rotten_flesh":31,"minecraft:stone_shovel":1,"minecraft:obsidian":5,"minecraft:rail":15,"minecraft:cobblestone":566,"minecraft:andesite":15,"minecraft:acacia_wood":1,"minecraft:oak_log":6,"minecraft:acacia_boat":9,"minecraft:gunpowder":2,"minecraft:cobblestone_stairs":5,"minecraft:dirt":982,"minecraft:leather_boots":1,"minecraft:bone":3,"minecraft:acacia_planks":158,"minecraft:apple":3,"minecraft:wheat_seeds":221,"minecraft:acacia_trapdoor":12,"minecraft:bell":1,"minecraft:iron_ingot":5,"minecraft:stone_pickaxe":1,"minecraft:tall_grass":1,"minecraft:oak_planks":8,"minecraft:acacia_sapling":36,"minecraft:dripstone_block":7,"minecraft:gravel":5,"minecraft:loom":1,"minecraft:acacia_stairs":2,"minecraft:spider_eye":22,"minecraft:leather_helmet":1,"minecraft:stone_axe":1,"minecraft:short_grass":1,"minecraft:granite":37,"minecraft:bone_meal":2,"minecraft:bread":42,"minecraft:emerald":3,"minecraft:oak_sapling":6,"minecraft:acacia_slab":102,"minecraft:melon_seeds":1,"minecraft:coal":95},"minecraft:broken":{"minecraft:leather_helmet":1,"minecraft:iron_shovel":1,"minecraft:golden_shovel":1,"minecraft:stone_hoe":1,"minecraft:stone_pickaxe":1,"minecraft:golden_axe":1,"minecraft:iron_axe":1,"minecraft:stone_axe":1,"minecraft:iron_pickaxe":2,"minecraft:wooden_axe":1,"minecraft:stone_shovel":2},"minecraft:crafted":{"minecraft:oak_planks":8,"minecraft:stone_shovel":2,"minecraft:furnace":2,"minecraft:cobblestone_stairs":36,"minecraft:iron_axe":2,"minecraft:ladder":3,"minecraft:rail":16,"minecraft:stone_hoe":2,"minecraft:minecart":1,"minecraft:crafting_table":6,"minecraft:acacia_slab":120,"minecraft:acacia_trapdoor":6,"minecraft:fletching_table":2,"minecraft:bucket":1,"minecraft:stone_axe":4,"minecraft:acacia_boat":1,"minecraft:air":0,"minecraft:stick":40,"minecraft:iron_ingot":41,"minecraft:iron_pickaxe":3,"minecraft:wooden_axe":1,"minecraft:iron_shovel":7,"minecraft:acacia_door":3,"minecraft:composter":2,"minecraft:acacia_planks":296,"minecraft:torch":4}},"DataVersion":3955}